ttui/__main__.py
ttui/app.py
ttui/cli.py
ttui/header.py
ttui/lib/filehandler_component.py
ttui/lib/utils.py
ttui/lib/valid.py
ttui/screens/about.py
ttui/screens/modals.py
ttui-0.1.2.dist-info/entry_points.txt
ttui-0.1.2.dist-info/LICENSE
ttui-0.1.2.dist-info/METADATA
ttui-0.1.2.dist-info/WHEEL
ttui-0.1.2.dist-info/RECORD
