Metadata-Version: 2.1
Name: ttui
Version: 0.1.2
Summary: A terminal .txt file viewer
License: MIT
Author: Andy Sit
Author-email: andysit173@gmail.com
Requires-Python: >=3.9,<4.0
Classifier: License :: OSI Approved :: MIT License
Classifier: Programming Language :: Python :: 3
Classifier: Programming Language :: Python :: 3.9
Classifier: Programming Language :: Python :: 3.10
Classifier: Programming Language :: Python :: 3.11
Classifier: Programming Language :: Python :: 3.12
Requires-Dist: asttokens (==2.4.1)
Requires-Dist: click (==8.1.7)
Requires-Dist: colorama (==0.4.6)
Requires-Dist: executing (==2.0.1)
Requires-Dist: icecream (==2.1.3)
Requires-Dist: linkify-it-py (==2.0.3)
Requires-Dist: markdown-it-py (==3.0.0)
Requires-Dist: mdit-py-plugins (==0.4.1)
Requires-Dist: mdurl (==0.1.2)
Requires-Dist: pygments (==2.18.0)
Requires-Dist: rich (==13.7.1)
Requires-Dist: six (==1.16.0)
Requires-Dist: textual (==0.76.0)
Requires-Dist: typing-extensions (==4.12.2)
Requires-Dist: uc-micro-py (==1.0.3)
